pyIsoP/__init__.py
pyIsoP/_version.py
pyIsoP/forcefields.py
pyIsoP/grid3D.py
pyIsoP/histo.py
pyIsoP/machlearn.py
pyIsoP/potentials.py
pyIsoP/predictor.py
pyIsoP/settings.py
pyIsoP/siter.py
pyIsoP/writer.py
pyIsoP/xyz.py
pyIsoP/data/README.md
pyIsoP/data/ZIF-4_mod.cif
pyIsoP/data/for_gpr_large.dat
pyIsoP/data/for_gpr_large_160.dat
pyIsoP/data/gprmodel_pyIsoP.joblib
pyIsoP/data/zif-4_replicated.pdb
pyIsoP/data/zif-4_repolicated.pdb
pyIsoP/tests/__init__.py
pyIsoP/tests/test_pyIsoP.py
pyIsoP-1.2.dist-info/LICENSE
pyIsoP-1.2.dist-info/METADATA
pyIsoP-1.2.dist-info/WHEEL
pyIsoP-1.2.dist-info/top_level.txt
pyIsoP-1.2.dist-info/RECORD
